odoo8_addon_partner_multi_company-8.0.1.0.1.99.dev2-py2.7-nspkg.pth
odoo8_addon_partner_multi_company-8.0.1.0.1.99.dev2.dist-info/DESCRIPTION.rst
odoo8_addon_partner_multi_company-8.0.1.0.1.99.dev2.dist-info/METADATA
odoo8_addon_partner_multi_company-8.0.1.0.1.99.dev2.dist-info/RECORD
odoo8_addon_partner_multi_company-8.0.1.0.1.99.dev2.dist-info/WHEEL
odoo8_addon_partner_multi_company-8.0.1.0.1.99.dev2.dist-info/metadata.json
odoo8_addon_partner_multi_company-8.0.1.0.1.99.dev2.dist-info/namespace_packages.txt
odoo8_addon_partner_multi_company-8.0.1.0.1.99.dev2.dist-info/top_level.txt
odoo_addons/partner_multi_company/README.rst
odoo_addons/partner_multi_company/__init__.py
odoo_addons/partner_multi_company/__openerp__.py
odoo_addons/partner_multi_company/hooks.py
odoo_addons/partner_multi_company/i18n/de.po
odoo_addons/partner_multi_company/i18n/es.po
odoo_addons/partner_multi_company/i18n/fr.po
odoo_addons/partner_multi_company/i18n/fr_FR.po
odoo_addons/partner_multi_company/i18n/partner_multi_company.pot
odoo_addons/partner_multi_company/i18n/sl.po
odoo_addons/partner_multi_company/models/__init__.py
odoo_addons/partner_multi_company/models/res_partner.py
odoo_addons/partner_multi_company/models/res_users.py
odoo_addons/partner_multi_company/static/description/icon.png
odoo_addons/partner_multi_company/tests/__init__.py
odoo_addons/partner_multi_company/tests/test_partner_multi_company.py
odoo_addons/partner_multi_company/views/res_partner_view.xml
